Metadata-Version: 1.1
Name: py-assembly
Version: 1.0.1
Summary: assemble project with all dependencies for install offline
Home-page: http://github.com/chaokunyang/py_assembly
Author: chaokunyang
Author-email: UNKNOWN
License: Apache License 2.0
Keywords: assembly dist offline install dependencies
Platform: UNKNOWN
Classifier: Programming Language :: Python :: 3.6
Classifier: Intended Audience :: Developers
